ytml/__init__.py
ytml/cli.py
ytml/animagic/__init__.py
ytml/animagic/html_preprocesor.py
ytml/animagic/renderer.py
ytml/animagic/test_renderer.py
ytml/conductor/__init__.py
ytml/conductor/conductor.py
ytml/conductor/local_server.py
ytml/conductor/sound_smith.py
ytml/conductor/test_conductor.py
ytml/conductor/vid_composer.py
ytml/interpretron/__init__.py
ytml/interpretron/parser.py
ytml/interpretron/test_parser.py
ytml/timesync/__init__.py
ytml/timesync/synchronizer.py
ytml/timesync/test_synchronizer.py
ytml/utils/__init__.py
ytml/utils/config.py
ytml/utils/ffmpeg_wizard.py
ytml/utils/logger.py
ytml/utils/utils.py
ytml/vocalforge/__init__.py
ytml/vocalforge/base_vocal_forge.py
ytml/vocalforge/gtts_vocal_forge.py
ytml/vocalforge/test_voice.py
ytml/vocalforge/xi_labs_vocal_forge.py
ytml_toolkit-0.2.0.dist-info/METADATA
ytml_toolkit-0.2.0.dist-info/WHEEL
ytml_toolkit-0.2.0.dist-info/entry_points.txt
ytml_toolkit-0.2.0.dist-info/top_level.txt
ytml_toolkit-0.2.0.dist-info/RECORD
