Metadata-Version: 2.2
Name: ytml-toolkit
Version: 0.2.0
Requires-Python: >=3.7
Requires-Dist: fastapi
Requires-Dist: uvicorn
Requires-Dist: websockets
Requires-Dist: boto3
Requires-Dist: gtts
Requires-Dist: pydub
Requires-Dist: moviepy
Requires-Dist: imageio
Requires-Dist: imageio-ffmpeg
Requires-Dist: playwright
Requires-Dist: numpy
Requires-Dist: requests
Requires-Dist: python-dotenv
Requires-Dist: beautifulsoup4
Requires-Dist: lxml
Requires-Dist: tqdm
Requires-Dist: pyttsx3
Requires-Dist: starlette
Requires-Dist: colorama
Requires-Dist: audioop-lts; python_version > "3.11"
Dynamic: requires-dist
Dynamic: requires-python
